markdown_readtime/__init__.py
markdown_readtime/__init__.pyi
markdown_readtime/markdown_readtime.cpython-312-x86_64-linux-gnu.so
markdown_readtime/py.typed
markdown_readtime-0.1.3.dist-info/METADATA
markdown_readtime-0.1.3.dist-info/WHEEL
markdown_readtime-0.1.3.dist-info/licenses/LICENSE
markdown_readtime-0.1.3.dist-info/RECORD
