Metadata-Version: 2.4
Name: markdown-readtime
Version: 0.1.3
Classifier: Development Status :: 4 - Beta
Classifier: Intended Audience :: Developers
Classifier: License :: OSI Approved :: MIT License
Classifier: Operating System :: OS Independent
Classifier: Programming Language :: Python
Classifier: Programming Language :: Python :: 3
Classifier: Programming Language :: Python :: 3.8
Classifier: Programming Language :: Python :: 3.9
Classifier: Programming Language :: Python :: 3.10
Classifier: Programming Language :: Python :: 3.11
Classifier: Programming Language :: Python :: 3.12
Classifier: Topic :: Text Processing
Classifier: Topic :: Software Development :: Libraries :: Python Modules
Requires-Dist: maturin>=1.11.5 ; extra == 'dev'
Provides-Extra: dev
License-File: LICENSE
Summary: A library to estimate reading time for Markdown content with support for Chinese and English texts
Keywords: markdown,reading-time,readtime,text-analysis
Author-email: hualayn <witity@hotmail.com>
License: MIT
Requires-Python: >=3.8
Project-URL: Homepage, https://github.com/hualayn/py-markdown-readtime
Project-URL: Repository, https://github.com/hualayn/py-markdown-readtime
